goofis_ardihikaru/__init__.py
goofis_ardihikaru/goofis.py
goofis_ardihikaru/dto/__init__.py
goofis_ardihikaru/dto/index_data.py
goofis_ardihikaru/dto/stock_data.py
goofis_ardihikaru/enums/__init__.py
goofis_ardihikaru/enums/currency_unit.py
goofis_ardihikaru/enums/language.py
goofis_ardihikaru/enums/price_change.py
goofis_ardihikaru/goofis/__init__.py
goofis_ardihikaru/goofis/coro/__init__.py
goofis_ardihikaru/goofis/coro/abc.py
goofis_ardihikaru/goofis/coro/index_parser.py
goofis_ardihikaru/goofis/coro/stock_parser.py
goofis_ardihikaru/goofis/sync/__init__.py
goofis_ardihikaru/goofis/sync/abc.py
goofis_ardihikaru/goofis/sync/index_parser.py
goofis_ardihikaru/goofis/sync/stock_parser.py
goofis_ardihikaru/utils/__init__.py
goofis_ardihikaru/utils/async_class.py
goofis_ardihikaru/utils/currency.py
goofis_ardihikaru/utils/my_html_parser.py
goofis_ardihikaru/utils/user_agent.py
goofis_ardihikaru/utils/utils.py
goofis_ardihikaru-0.0.48.dist-info/LICENSE.txt
goofis_ardihikaru-0.0.48.dist-info/METADATA
goofis_ardihikaru-0.0.48.dist-info/WHEEL
goofis_ardihikaru-0.0.48.dist-info/top_level.txt
goofis_ardihikaru-0.0.48.dist-info/RECORD
