Metadata-Version: 2.1
Name: goofis-ardihikaru
Version: 0.0.48
Summary: Modules to extract information from Google Finance
Home-page: https://pypi.org/project/goofis-ardihikaru/0.0.1/#files
Author: Muhammad Febrian Ardiansyah
Author-email: mfardiansyah@outlook.com
License: MIT
Keywords: asyncio
Platform: any
Classifier: Development Status :: 3 - Alpha
Classifier: Intended Audience :: Developers
Classifier: Programming Language :: Python :: 3
Classifier: License :: OSI Approved :: MIT License
Classifier: Operating System :: OS Independent
Requires-Python: >=3.8
License-File: LICENSE.txt
Requires-Dist: ujson ==5.8.0
Requires-Dist: requests ==2.31.0
Requires-Dist: parsel ==1.8.1
Requires-Dist: fake-useragent ==1.2.1
Requires-Dist: simplejson ==3.19.1
